MANIFEST.in
setup.cfg
setup.py
jotit/__init__.py
jotit/defaults.yml
jotit/jotit.py
jotit.egg-info/PKG-INFO
jotit.egg-info/SOURCES.txt
jotit.egg-info/dependency_links.txt
jotit.egg-info/not-zip-safe
jotit.egg-info/requires.txt
jotit.egg-info/top_level.txt
jotit/static/__init__.py
jotit/static/humans.txt
jotit/templates/__init__.py
jotit/templates/base.html
jotit/templates/content.html
jotit/templates/error.html
jotit/templates/index.html
jotit/templates/login.html