Metadata-Version: 1.1
Name: jotit
Version: 0.1.3
Summary: Super minimal file-based CMS
Home-page: https://github.com/nkantar/jotit
Author: Nikola Kantar
Author-email: nik@nkantar.com
License: GPLv3
Download-URL: https://github.com/nkantar/jotit/tarball/0.1.3
Keywords: cms,markdown
Platform: UNKNOWN
